LICENSE
MANIFEST.in
README.md
setup.py
django_referral.egg-info/PKG-INFO
django_referral.egg-info/SOURCES.txt
django_referral.egg-info/dependency_links.txt
django_referral.egg-info/top_level.txt
referral/__init__.py
referral/admin.py
referral/compat.py
referral/middleware.py
referral/models.py
referral/settings.py
referral/migrations/0001_initial.py
referral/migrations/__init__.py
referral/south_migrations/0001_initial.py
referral/south_migrations/0002_auto__add_field_campaign_pattern.py
referral/south_migrations/__init__.py
referral/tests/__init__.py
referral/tests/factories.py
referral/tests/settings.py
referral/tests/test_middlewares.py
referral/tests/test_models.py