Metadata-Version: 1.1
Name: django-referral
Version: 1.0.1
Summary: A small django application for marketing using referral links
Home-page: https://github.com/byteweaver/django-referral
Author: akuryou
Author-email: contact@byteweaver.net
License: Copyright (c) 2014 byteweaver
